{
  "name": "Light Blossom",
  "description": "A beautiful light pink theme, made for people who love pink but prefer a brighter interface.",
  "version": "1",
  "authors": [
    {
      "name": "kmmiio99o.dev",
      "id": "879393496627306587"
    }
  ],
  "semanticColors": {
    "ANDROID_RIPPLE": ["#f0a9c9"],
    "CHAT_BACKGROUND": ["#f5dfe9"],
    "BACKGROUND_ACCENT": ["#f2c5da"],
    "BACKGROUND_FLOATING": ["#f5dae7"],
    "BACKGROUND_MENTIONED": ["#f0a9c933"],
    "BACKGROUND_MENTIONED_HOVER": ["#f0a9c94d"],
    "SCROLLBAR_THIN_THUMB": ["#f0a9c9"],
    "SCROLLBAR_THIN_TRACK": ["transparent"],
    "SCROLLBAR_AUTO_THUMB": ["#f0a9c9"],
    "SCROLLBAR_AUTO_TRACK": ["transparent"],
    "CHANNELTEXTAREA_BACKGROUND": ["#f5dae7"],
    "REDESIGN_ACTIVITY_CARD_BACKGROUND": ["#f5dfe9"],
    "REDESIGN_ACTIVITY_CARD_BACKGROUND_PRESSED": ["#f2c5da"],
    "CHANNELS_DEFAULT": ["#5C3753"],
    "BACKGROUND_MESSAGE_HOVER": ["hsla(333, 90%, 88%, 0.5)"],
    "BACKGROUND_NESTED_FLOATING": ["#f5dae7"],
    "BACKGROUND_MOBILE_PRIMARY": ["#f8e9ef"],
    "BACKGROUND_MOBILE_SECONDARY": ["#f5dfe9"],
    "BACKGROUND_MODIFIER_ACCENT": ["hsla(333, 90%, 88%, 0.3)"],
    "BACKGROUND_MODIFIER_ACTIVE": ["hsla(333, 90%, 83%, 0.5)"],
    "BACKGROUND_MODIFIER_HOVER": ["hsla(333, 90%, 88%, 0.3)"],
    "BACKGROUND_MODIFIER_SELECTED": ["hsla(333, 90%, 83%, 0.5)"],
    "BACKGROUND_PRIMARY": ["#f8e9ef"],
    "BACKGROUND_SECONDARY": ["#f5dfe9"],
    "BACKGROUND_SECONDARY_ALT": ["#f5dae7"],
    "BACKGROUND_TERTIARY": ["#f2c5da"],
    "BG_BASE_PRIMARY": ["#f8e9ef"],
    "BG_BACKDROP": ["#f5dfe9b2"],
    "BG_BASE_SECONDARY": ["#f8e9ef"],
    "BG_BASE_TERTIARY": ["#f5dfe9"],
    "HOME_BACKGROUND": ["#f5dfe9"],
    "BORDER_FAINT": ["hsla(333, 90%, 88%, 0.3)"],
    "BORDER_STRONG": ["hsla(333, 75%, 80%, 0.5)"],
    "BORDER_SUBTLE": ["hsla(333, 75%, 80%, 0.5)"],
    "CARD_SECONDARY_BG": ["#f5dae7"],
    "CARD_PRIMARY_BG": ["#f5dfe9"],
    "CHANNEL_ICON": ["#5C3753"],
    "EMBED_BACKGROUND": ["#f5dae7"],
    "HEADER_PRIMARY": ["#5C3753"],
    "HEADER_SECONDARY": ["#5C3753"],
    "INTERACTIVE_ACTIVE": ["#d44d76"],
    "INTERACTIVE_HOVER": ["#d44d76"],
    "INTERACTIVE_MUTED": ["#5C375366"],
    "INTERACTIVE_NORMAL": ["#5C3753"],
    "MENTION_BACKGROUND": ["#ff4d9433"],
    "MENTION_FOREGROUND": ["#ff4d94"],
    "REDESIGN_BUTTON_SECONDARY_ALT_BACKGROUND": ["#f5dae7"],
    "REDESIGN_BUTTON_SECONDARY_BACKGROUND": ["#f5dae7"],
    "REDESIGN_BUTTON_SECONDARY_BORDER": ["hsla(333, 75%, 80%, 0.5)"],
    "REDESIGN_BUTTON_DANGER_BACKGROUND": ["#d44d76"],
    "REDESIGN_CHANNEL_CATEGORY_NAME_TEXT": ["#5C3753"],
    "REDESIGN_CHANNEL_NAME_TEXT": ["#5C3753"],
    "REDESIGN_CHAT_INPUT_BACKGROUND": ["#f5dae7"],
    "SPOILER_HIDDEN_BACKGROUND": ["#f5dae7"],
    "STATUS_DANGER": ["#d44d76"],
    "STATUS_DANGER_BACKGROUND": ["#d44d76"],
    "STATUS_DANGER_TEXT": ["#ffffff"],
    "POLLS_NORMAL_FILL_HOVER": ["#f5dae7"],
    "POLLS_NORMAL_IMAGE_BACKGROUND": ["#f5dae7"],
    "POLLS_VICTOR_FILL": ["#f2c5da80"],
    "TEXT_LINK": ["#d44d76"],
    "TEXT_MUTED": ["#5C375366"],
    "TEXT_NORMAL": ["#5C3753"],
    "TEXT_PRIMARY": ["#5C3753"],
    "TEXT_SECONDARY": ["#5C3753"],
    "BG_MOD_FAINT": ["hsla(333, 90%, 88%, 0.3)"],
    "KEYBOARD": ["#f5dae7"],
    "BACKGROUND_MODIFIER_ACCEPT": ["#f2c5da33"],
    "BACKGROUND_MODIFIER_ACCEPT_HOVER": ["#f2c5da4d"],
    "AUTOMOD_QUEUED FOR_REVIEW_BACKGROUND": ["#ff4d9433"],
    "AUTOMOD_QUEUED FOR_REVIEW_BACKGROUND_HOVER": ["#ff4d944d"]
  },
  "rawColors": {
    "BLUE_260": "#f0a9c9",
    "BLUE_300": "#f0a9c9",
    "BLUE_330": "#f0a9c9",
    "BLUE_345": "#f0a9c9",
    "BLUE_360": "#f0a9c9",
    "BLUE_400": "#f0a9c9",
    "BLUE_430": "#f0a9c9",
    "BLUE_460": "#f0a9c9",
    "BLUE_500": "#f0a9c9",
    "BLUE_530": "#f0a9c9",
    "BLUE_560": "#f0a9c9",
    "BLUE_600": "#f0a9c9",
    "BLUE_630": "#f0a9c9",
    "BLUE_660": "#f0a9c9",
    "BLUE_700": "#f0a9c9",
    "BLACK_500": "#f5dfe9b2",
    "BRAND_200": "#d44d76",
    "BRAND_260": "#d44d76",
    "BRAND_300": "#d44d76",
    "BRAND_330": "#d44d76",
    "BRAND_345": "#d44d76",
    "BRAND_360": "#d44d76",
    "BRAND_400": "#d44d76",
    "BRAND_430": "#d44d76",
    "BRAND_460": "#d44d76",
    "BRAND_500": "#d44d76",
    "BRAND_530": "#d44d76",
    "BRAND_560": "#d44d76",
    "BRAND_600": "#d44d76",
    "BRAND_630": "#d44d76",
    "BRAND_660": "#d44d76",
    "BRAND_700": "#d44d76",
    "BRAND_730": "#d44d76",
    "PLUM_1": "#d44d76",
    "PLUM_10": "#5C3753",
    "PLUM_11": "#5C3753",
    "PLUM_13": "#5C3753",
    "PLUM_15": "#d44d76",
    "PLUM_16": "#f5dfe9",
    "PLUM_17": "#f8e9ef",
    "PLUM_18": "#f5dfe9",
    "PLUM_19": "#f5dfe9",
    "PLUM_20": "#f8e9ef",
    "PLUM_21": "#f5dfe9",
    "PLUM_22": "#f5dfe9",
    "PLUM_24": "#f8e9ef",
    "PLUM_25": "#f8e9ef",
    "PLUM_3": "#d44d76",
    "PLUM_4": "#d44d76",
    "PLUM_6": "#d44d76",
    "PLUM_9": "#5C3753",
    "PRIMARY_100": "#d44d76",
    "PRIMARY_200": "#d44d76",
    "PRIMARY_300": "#d44d76",
    "PRIMARY_330": "#d44d76",
    "PRIMARY_360": "#d44d76",
    "PRIMARY_400": "#d44d76",
    "PRIMARY_460": "#f5dae7",
    "PRIMARY_500": "#d44d76",
    "PRIMARY_530": "#d44d76",
    "PRIMARY_600": "#f8e9ef",
    "PRIMARY_630": "#f5dfe9",
    "PRIMARY_645": "#f8e9ef",
    "PRIMARY_660": "#f5dfe9",
    "PRIMARY_700": "#f5dfe9",
    "PRIMARY_730": "#5C3753",
    "PRIMARY_800": "#f5dfe9",
    "GREEN_260": "#f2c5da",
    "GREEN_300": "#f2c5da",
    "GREEN_330": "#f2c5da",
    "GREEN_345": "#f2c5da",
    "GREEN_360": "#f2c5da",
    "GREEN_400": "#f2c5da",
    "GREEN_430": "#f2c5da",
    "GREEN_460": "#f2c5da",
    "GREEN_500": "#f2c5da",
    "GREEN_530": "#f2c5da",
    "GREEN_560": "#f2c5da",
    "GREEN_600": "#f2c5da",
    "GREEN_630": "#f2c5da",
    "GREEN_660": "#f2c5da",
    "GREEN_700": "#f2c5da",
    "GUILD_BOOSTING_PINK": "#d44d76",
    "GUILD_BOOSTING_PURPLE": "#d44d76",
    "GUILD_BOOSTING_PURPLE_FOR_GRADIENTS": "#d44d76",
    "RED_260": "#d44d76",
    "RED_300": "#d44d76",
    "RED_330": "#d44d76",
    "RED_345": "#d44d76",
    "RED_360": "#d44d76",
    "RED_400": "#d44d76",
    "RED_430": "#d44d76",
    "RED_460": "#d44d76",
    "RED_500": "#d44d76",
    "RED_530": "#d44d76",
    "RED_560": "#d44d76",
    "RED_600": "#d44d76",
    "RED_630": "#d44d76",
    "RED_660": "#d44d76",
    "RED_700": "#d44d76",
    "ROLE_DEFAULT": "#5C3753",
    "ORANGE_260": "#f0a9c9",
    "ORANGE_300": "#f0a9c9",
    "ORANGE_330": "#f0a9c9",
    "ORANGE_345": "#f0a9c9",
    "ORANGE_360": "#f0a9c9",
    "ORANGE_400": "#f0a9c9",
    "ORANGE_430": "#f0a9c9",
    "ORANGE_460": "#f0a9c9",
    "ORANGE_500": "#f0a9c9",
    "ORANGE_530": "#f0a9c9",
    "ORANGE_560": "#f0a9c9",
    "ORANGE_600": "#f0a9c9",
    "ORANGE_630": "#f0a9c9",
    "ORANGE_660": "#f0a9c9",
    "ORANGE_700": "#f0a9c9",
    "YELLOW_260": "#f0a9c9",
    "YELLOW_300": "#f0a9c9",
    "YELLOW_330": "#f0a9c9",
    "YELLOW_345": "#f0a9c9",
    "YELLOW_360": "#f0a9c9",
    "YELLOW_400": "#f0a9c9",
    "YELLOW_430": "#f0a9c9",
    "YELLOW_460": "#f0a9c9",
    "YELLOW_500": "#f0a9c9",
    "YELLOW_530": "#f0a9c9",
    "YELLOW_560": "#f0a9c9",
    "YELLOW_600": "#f0a9c9",
    "YELLOW_630": "#f0a9c9",
    "YELLOW_660": "#f0a9c9",
    "YELLOW_700": "#f0a9c9",
    "WHITE_500": "#d44d76",
    "WHITE_630": "#5C3753"
  },
  "plus": {
    "version": "0",
    "iconPack": "",
    "mentionLineColor": "#d44d76",
    "customOverlays": true,
    "icons": {
      "trash": "#d44d76",
      "TrashIcon": "#d44d76",
      "TriangleExclamationPointIcon": "#d44d76",
      "toast_copy_link": "#f0a9c9",
      "toast_copy_message": "#5C3753",
      "toast_image_saved": "#5C3753"
    }
  },
  "spec": 2
}
